nhlstats/__init__.py
nhlstats/__version__.py
nhlstats/apiclient.py
nhlstats/constants.py
nhlstats/normalizers.py
nhlstats/cli/__init__.py
nhlstats/cli/core.py
nhlstats/cli/helpers.py
nhlstats/cli/output.py
nhlstats/formatters/__init__.py
nhlstats/formatters/csv.py
nhlstats/formatters/json.py
nhlstats/formatters/text.py
nhlstats-0.3.0.dist-info/LICENSE
nhlstats-0.3.0.dist-info/METADATA
nhlstats-0.3.0.dist-info/WHEEL
nhlstats-0.3.0.dist-info/entry_points.txt
nhlstats-0.3.0.dist-info/top_level.txt
nhlstats-0.3.0.dist-info/RECORD
