Metadata-Version: 2.1
Name: nhlstats
Version: 0.3.0
Summary: Tools for collecting NHL play-by-play stats.
Home-page: https://github.com/tomplex/nhlstats
Author: Tom Caruso
Author-email: carusot42@gmail.com
License: UNKNOWN
Platform: UNKNOWN
Classifier: Programming Language :: Python
Classifier: Programming Language :: Python :: 3
Classifier: Programming Language :: Python :: Implementation :: CPython
Requires-Dist: click
Requires-Dist: requests
Requires-Dist: tabulate
